Metadata-Version: 1.2
Name: aetacsdcscsdcawacab
Version: 1.0.0
Summary: nothing
Home-page: https://www.python.org/
Author: lingshiyinzi
Author-email: 294594605@qq.com
License: MIT
Keywords: www
Platform: UNKNOWN
Requires-Python: >=3
